contoml/__init__.py
contoml/_version.py
contoml/errors.py
contoml/test_prettifier.py
contoml/test_util.py
contoml/util.py
contoml/elements/__init__.py
contoml/elements/abstracttable.py
contoml/elements/array.py
contoml/elements/atomic.py
contoml/elements/common.py
contoml/elements/errors.py
contoml/elements/factory.py
contoml/elements/inlinetable.py
contoml/elements/metadata.py
contoml/elements/table.py
contoml/elements/tableheader.py
contoml/elements/test_array.py
contoml/elements/test_atomic.py
contoml/elements/test_common.py
contoml/elements/test_factory.py
contoml/elements/test_inlinetable.py
contoml/elements/test_metadata.py
contoml/elements/test_table.py
contoml/elements/test_tableheader.py
contoml/elements/test_traversal.py
contoml/elements/traversal/__init__.py
contoml/elements/traversal/predicates.py
contoml/file/__init__.py
contoml/file/array.py
contoml/file/cascadedict.py
contoml/file/file.py
contoml/file/freshtable.py
contoml/file/peekableit.py
contoml/file/raw.py
contoml/file/structurer.py
contoml/file/test_cascadedict.py
contoml/file/test_entries.py
contoml/file/test_peekableit.py
contoml/file/test_structurer.py
contoml/file/toplevels.py
contoml/lexer/__init__.py
contoml/lexer/test_lexer.py
contoml/parser/__init__.py
contoml/parser/elementsanitizer.py
contoml/parser/errors.py
contoml/parser/parser.py
contoml/parser/recdesc.py
contoml/parser/test_parser.py
contoml/parser/tokenstream.py
contoml/prettifier/__init__.py
contoml/prettifier/anontableindent.py
contoml/prettifier/commentspace.py
contoml/prettifier/linelength.py
contoml/prettifier/tableassignment.py
contoml/prettifier/tableindent.py
contoml/prettifier/tablesep.py
contoml/prettifier/tablesort.py
contoml/prettifier/test_anontableindent.py
contoml/prettifier/test_commentspace.py
contoml/prettifier/test_linelength.py
contoml/prettifier/test_tableassignment.py
contoml/prettifier/test_tableindent.py
contoml/prettifier/test_tablesep.py
contoml-0.32.dist-info/DESCRIPTION.rst
contoml-0.32.dist-info/METADATA
contoml-0.32.dist-info/RECORD
contoml-0.32.dist-info/WHEEL
contoml-0.32.dist-info/metadata.json
contoml-0.32.dist-info/top_level.txt
